MANIFEST.in
README.rst
setup.cfg
setup.py
django_stylus_watcher.egg-info/PKG-INFO
django_stylus_watcher.egg-info/SOURCES.txt
django_stylus_watcher.egg-info/dependency_links.txt
django_stylus_watcher.egg-info/not-zip-safe
django_stylus_watcher.egg-info/requires.txt
django_stylus_watcher.egg-info/top_level.txt
stylus_watcher/__init__.py
stylus_watcher/watcher.py
stylus_watcher/management/__init__.py
stylus_watcher/management/commands/__init__.py
stylus_watcher/management/commands/stylus_watcher.py