Metadata-Version: 1.1
Name: django-stylus-watcher
Version: 1.0.6
Summary: Django stylus watchers & auto compilers
Home-page: http://github.com/dalou/django-stylus-watcher
Author: Autrusseau Damien
Author-email: autrusseau.damien@gmail.com
License: MIT
Platform: UNKNOWN
Classifier: Development Status :: 5 - Production/Stable
Classifier: Environment :: Web Environment
Classifier: Intended Audience :: Developers
Classifier: License :: OSI Approved :: BSD License
Classifier: Operating System :: OS Independent
Classifier: Programming Language :: Python
Classifier: Framework :: Django
